postcodes_io_api/__init__.py
postcodes_io_api/api.py
tests/__init__.py
tests/test.py
postcodes_io_api-0.0.4.dist-info/LICENSE
postcodes_io_api-0.0.4.dist-info/METADATA
postcodes_io_api-0.0.4.dist-info/WHEEL
postcodes_io_api-0.0.4.dist-info/top_level.txt
postcodes_io_api-0.0.4.dist-info/RECORD
